ssrs_library/__init__.py
ssrs_library/credential_manager.py
ssrs_library/datasource_manager.py
ssrs_library/security_manager.py
ssrs_library/ssrs_library.py
ssrs_library/types/datasourcetype.py
ssrs_library/types/rscredentials.py
ssrs_library/types/rsdatasource.py
ssrs_library/types/rsitem.py
ssrs_library/types/rsitemtype.py
ssrs_library/types/security.py
ssrs_powerbi_library-1.2.0.dist-info/METADATA
ssrs_powerbi_library-1.2.0.dist-info/WHEEL
ssrs_powerbi_library-1.2.0.dist-info/top_level.txt
ssrs_powerbi_library-1.2.0.dist-info/RECORD
