Metadata-Version: 2.1
Name: ssrs-powerbi-library
Version: 1.2.0
Summary: SSRS Library
Author-email: ipierre1 <59824069+ipierre1@users.noreply.github.com>
License: MIT License
Project-URL: Homepage, https://github.com/ipierre1/ssrs-powerbi-library
Project-URL: Issues, https://github.com/ipierre1/ssrs-powerbi-library/issues
Classifier: Development Status :: 4 - Beta
Classifier: Intended Audience :: Developers
Classifier: Programming Language :: Python :: 3
Classifier: Programming Language :: Python :: 3.7
Classifier: Programming Language :: Python :: 3.8
Classifier: Programming Language :: Python :: 3.9
Classifier: Programming Language :: Python :: 3.10
Classifier: Programming Language :: Python :: 3.11
Requires-Python: >=3.7
